d4k_ms_service/__info__.py
d4k_ms_service/__init__.py
d4k_ms_service/neo4j_connection.py
d4k_ms_service/node.py
d4k_ms_service-0.2.0.dist-info/licenses/LICENSE
d4k_ms_service-0.2.0.dist-info/METADATA
d4k_ms_service-0.2.0.dist-info/WHEEL
d4k_ms_service-0.2.0.dist-info/top_level.txt
d4k_ms_service-0.2.0.dist-info/RECORD
